notetask/__init__.py
notetask/task/__init__.py
notetask/task/task1.py
notetask-0.0.5.dist-info/METADATA
notetask-0.0.5.dist-info/WHEEL
notetask-0.0.5.dist-info/top_level.txt
notetask-0.0.5.dist-info/RECORD
