Metadata-Version: 2.1
Name: notetask
Version: 0.0.5
Summary: notetask
Home-page: https://github.com/1007530194
Author: bingtao
Author-email: 1007530194@qq.com
License: UNKNOWN
Platform: UNKNOWN
Requires-Dist: tqdm
Requires-Dist: noteodps
Requires-Dist: pyodps
Requires-Dist: pandas
